LICENSE
MANIFEST.in
NOTES
setup.py
bin/idio
idiopidae/__init__.py
idiopidae/parser.py
idiopidae/runtime.py
idiopidae.egg-info/PKG-INFO
idiopidae.egg-info/SOURCES.txt
idiopidae.egg-info/dependency_links.txt
idiopidae.egg-info/top_level.txt
tests/data/output.html
tests/data/test.py
tests/idiopidae_tests/__init__.py
tests/idiopidae_tests/parser_test.py
tests/idiopidae_tests/scanner_test.py
tests/runtime_tests/__init__.py
tests/runtime_tests/builder_test.py
tests/runtime_tests/composer_test.py
